{
  "id": "",
  "name": "",
  "font_family": "iconfont",
  "css_prefix_text": "icon-",
  "description": "",
  "glyphs": [
    {
      "icon_id": "852113",
      "name": "工具箱",
      "font_class": "gongjuxiang",
      "unicode": "e607",
      "unicode_decimal": 58887
    },
    {
      "icon_id": "902029",
      "name": "标签",
      "font_class": "biaoqian",
      "unicode": "e62b",
      "unicode_decimal": 58923
    },
    {
      "icon_id": "956743",
      "name": "留言",
      "font_class": "msg",
      "unicode": "e61d",
      "unicode_decimal": 58909
    },
    {
      "icon_id": "1135940",
      "name": "用户",
      "font_class": "yonghu",
      "unicode": "e612",
      "unicode_decimal": 58898
    },
    {
      "icon_id": "1277697",
      "name": "首页",
      "font_class": "shouye",
      "unicode": "e653",
      "unicode_decimal": 58963
    },
    {
      "icon_id": "7193682",
      "name": "图片",
      "font_class": "tupian",
      "unicode": "e730",
      "unicode_decimal": 59184
    },
    {
      "icon_id": "8802618",
      "name": "日历",
      "font_class": "rili",
      "unicode": "e642",
      "unicode_decimal": 58946
    },
    {
      "icon_id": "9712613",
      "name": "密码",
      "font_class": "mima",
      "unicode": "e6a8",
      "unicode_decimal": 59048
    },
    {
      "icon_id": "11125633",
      "name": "文章",
      "font_class": "16",
      "unicode": "e625",
      "unicode_decimal": 58917
    },
    {
      "icon_id": "11749453",
      "name": "更新",
      "font_class": "gengxin",
      "unicode": "e68f",
      "unicode_decimal": 59023
    }
  ]
}
